setup.py
tigran_test3/__init__.py
tigran_test3.egg-info/PKG-INFO
tigran_test3.egg-info/SOURCES.txt
tigran_test3.egg-info/dependency_links.txt
tigran_test3.egg-info/requires.txt
tigran_test3.egg-info/top_level.txt